adhoc_interface/__init__.py
adhoc_interface/validation.py
adhoc_interface-0.0.2.dist-info/LICENSE
adhoc_interface-0.0.2.dist-info/METADATA
adhoc_interface-0.0.2.dist-info/WHEEL
adhoc_interface-0.0.2.dist-info/top_level.txt
adhoc_interface-0.0.2.dist-info/RECORD
